{"prefix":"-","modRole":"344851801981583360","adminRole":"344679884100075521","disabledCommands":[],"modlogs":"354551114412195841","welcomeChannel":"344537044154056714","filterInvites":true,"welcomeMessage":"Welcome to the **%SERVER%**, a place to discuss I&FR. Have fun here, **%MEMBER%**","swearWords":[],"mentionThreshold":15,"leaveMessage":"**%MEMBERNAME%** just left **%SERVER%**. Bye bye **%MEMBERNAME%**...","announcementRole":null,"announcementChannel":null,"autoRole":null,"id":"344537043654672406","pointsSystem":null,"logChannel":null,"PublicRoles":[],"starboard":null}
